s3_iterator/__init__.py
s3_iterator/iterator.py
s3_iterator/list_obj.py
s3_iterator/smart_worker.py
s3_iterator/worker.py
s3_iterator_kypkalorian-0.0.6.dist-info/METADATA
s3_iterator_kypkalorian-0.0.6.dist-info/WHEEL
s3_iterator_kypkalorian-0.0.6.dist-info/top_level.txt
s3_iterator_kypkalorian-0.0.6.dist-info/RECORD
