Metadata-Version: 2.1
Name: s3-iterator-kypkalorian
Version: 0.0.6
Summary: A package for iterating through s3
Home-page: https://github.com/kypkalorian/s3_iterator
Author: anonymous_donkey_1337
Author-email: colin.baxter13@gmail.com
License: UNKNOWN
Platform: UNKNOWN
Classifier: Programming Language :: Python :: 3
Classifier: License :: OSI Approved :: MIT License
Classifier: Operating System :: OS Independent
